py_canoe/__init__.py
py_canoe/logging_collection.py
py_canoe/py_canoe.py
py_canoe/py_canoe_logger.py
py_canoe-3.0.3.dist-info/LICENSE
py_canoe-3.0.3.dist-info/METADATA
py_canoe-3.0.3.dist-info/WHEEL
py_canoe-3.0.3.dist-info/RECORD
