Metadata-Version: 2.3
Name: py_canoe
Version: 3.0.3
Summary: Python CANoe Package
License: LICENSE
Keywords: Vector,CANoe,py_canoe
Author: chaitu-ycr
Author-email: chaitu.ycr@gmail.com
Requires-Python: >=3.9,<4.0
Classifier: License :: OSI Approved :: MIT License
Classifier: License :: Other/Proprietary License
Classifier: Operating System :: Microsoft :: Windows
Classifier: Programming Language :: Python :: 3
Classifier: Programming Language :: Python :: 3.9
Classifier: Programming Language :: Python :: 3.10
Classifier: Programming Language :: Python :: 3.11
Classifier: Programming Language :: Python :: 3.12
Classifier: Programming Language :: Python :: 3.13
Classifier: Topic :: Software Development :: Embedded Systems
Requires-Dist: pywin32 (>=306,<=308)
Project-URL: Documentation, https://chaitu-ycr.github.io/py_canoe/
Project-URL: Homepage, https://github.com/chaitu-ycr/py_canoe
Project-URL: Repository, https://github.com/chaitu-ycr/py_canoe
